mcp_llm_bridge/__init__.py
mcp_llm_bridge/bridge.py
mcp_llm_bridge/config.py
mcp_llm_bridge/create_test_db.py
mcp_llm_bridge/llm_client.py
mcp_llm_bridge/main.py
mcp_llm_bridge/mcp_client.py
mcp_llm_bridge/tools.py
orange_mcp_llm_bridge-0.1.0.dist-info/licenses/LICENSE.md
orange_mcp_llm_bridge-0.1.0.dist-info/METADATA
orange_mcp_llm_bridge-0.1.0.dist-info/WHEEL
orange_mcp_llm_bridge-0.1.0.dist-info/top_level.txt
orange_mcp_llm_bridge-0.1.0.dist-info/RECORD
